fuzzyfloat/__init__.py
fuzzyfloat/meta.py
fuzzyfloat/types.py
fuzzyfloat-1.0.3.dist-info/METADATA
fuzzyfloat-1.0.3.dist-info/RECORD
fuzzyfloat-1.0.3.dist-info/WHEEL
fuzzyfloat-1.0.3.dist-info/top_level.txt
fuzzyfloat-1.0.3.dist-info/zip-safe
