Metadata-Version: 2.1
Name: fuzzyfloat
Version: 1.0.3
Summary: Utility library that provides a floating point type with tolerance for equality comparisons
Home-page: https://github.com/keystonetowersystems/fuzzyfloat
Author: Greg Echelberger
Author-email: greg@keystonetowersystems.com
License: UNKNOWN
Platform: UNKNOWN
Classifier: Programming Language :: Python :: 3 :: Only
Classifier: License :: OSI Approved :: MIT License
Classifier: Topic :: Scientific/Engineering
Classifier: Topic :: Software Development :: Libraries
Classifier: Operating System :: OS Independent
Classifier: Intended Audience :: Developers
Classifier: Intended Audience :: Science/Research
Requires-Python: >=3
